common_robotics_utilities/__init__.py
common_robotics_utilities/libcommon_robotics_utilities.a
common_robotics_utilities/common_robotics_utilities.cpython-310-x86_64-linux-gnu.so
common_robotics_utilities-2023.6.3.dist-info/METADATA
common_robotics_utilities-2023.6.3.dist-info/LICENSE
common_robotics_utilities-2023.6.3.dist-info/top_level.txt
common_robotics_utilities-2023.6.3.dist-info/RECORD
common_robotics_utilities-2023.6.3.dist-info/WHEEL
common_robotics_utilities.libs/libgomp-a34b3233.so.1.0.0
