Metadata-Version: 2.1
Name: common-robotics-utilities
Version: 2023.6.3
License-File: LICENSE
Requires-Dist: numpy
